sm2mpx/__init__.py
sm2mpx/sm2mpx.py
sm2mpx-0.1.0.data/scripts/sm2mpx
sm2mpx-0.1.0.dist-info/LICENSE
sm2mpx-0.1.0.dist-info/METADATA
sm2mpx-0.1.0.dist-info/WHEEL
sm2mpx-0.1.0.dist-info/top_level.txt
sm2mpx-0.1.0.dist-info/RECORD
