Metadata-Version: 2.1
Name: sm2mpx
Version: 0.1.0
Summary: A python 3 unpacker for sm2mpx files.
Home-page: https://gitlab.com/menschel/sm2mpx
Author: Patrick Menschel
Author-email: menschel.p@posteo.de
Keywords: game data sm2mpx
Classifier: Development Status :: 4 - Beta
Classifier: Programming Language :: Python :: 3 :: Only
Classifier: License :: OSI Approved :: GNU General Public License v3 or later (GPLv3+)
Classifier: Operating System :: OS Independent
Classifier: Intended Audience :: Developers
Classifier: Topic :: Scientific/Engineering
Classifier: Topic :: Software Development :: Embedded Systems
Requires-Python: >=3.9
License-File: LICENSE
